bltzr/__init__.py
bltzr/dataset.py
bltzr/tokenizer.py
bltzr-0.2.5.dist-info/LICENSE
bltzr-0.2.5.dist-info/WHEEL
bltzr-0.2.5.dist-info/METADATA
bltzr-0.2.5.dist-info/RECORD
